mujoco_viewer/__init__.py
mujoco_viewer/callbacks.py
mujoco_viewer/mujoco_viewer.py
multi_panel_mujoco_pyviewer-1.0.5.dist-info/METADATA
multi_panel_mujoco_pyviewer-1.0.5.dist-info/WHEEL
multi_panel_mujoco_pyviewer-1.0.5.dist-info/top_level.txt
multi_panel_mujoco_pyviewer-1.0.5.dist-info/RECORD
