Metadata-Version: 2.4
Name: multi_panel_mujoco_pyviewer
Version: 1.0.5
Summary: Multi-panels render viewer for MuJoCo Python
Home-page: https://github.com/gaolongsen/multi-panel_mujoco-pyviewer
Author: Longsen Gao
Author-email: Longsen Gao <longsengao@gmail.com>
License: BSD 2-Clause License
Project-URL: Homepage, https://github.com/gaolongsen/multi-panel_mujoco-pyviewer
Project-URL: Bug Tracker, https://github.com/gaolongsen/multi-panel_mujoco-pyviewer/issues
Classifier: Development Status :: 3 - Alpha
Classifier: Intended Audience :: Developers
Classifier: Topic :: Software Development :: Libraries :: Python Modules
Classifier: License :: OSI Approved :: MIT License
Classifier: Programming Language :: Python :: 3
Classifier: Programming Language :: Python :: 3.7
Classifier: Programming Language :: Python :: 3.8
Classifier: Programming Language :: Python :: 3.9
Classifier: Programming Language :: Python :: 3.10
Classifier: Programming Language :: Python :: 3.11
Classifier: Programming Language :: Python :: 3.12
Classifier: Operating System :: OS Independent
Requires-Python: >=3.6
Requires-Dist: mujoco>=2.1.5
Requires-Dist: glfw>=2.5.0
Requires-Dist: imageio
Requires-Dist: pyyaml
Dynamic: author
Dynamic: home-page
Dynamic: requires-python
